mt5_bridge/__init__.py
mt5_bridge/client.py
mt5_bridge/main.py
mt5_bridge/mcp_server.py
mt5_bridge/mt5_handler.py
mt5_bridge-1.2.0.dist-info/METADATA
mt5_bridge-1.2.0.dist-info/WHEEL
mt5_bridge-1.2.0.dist-info/entry_points.txt
mt5_bridge-1.2.0.dist-info/licenses/LICENSE
mt5_bridge-1.2.0.dist-info/RECORD
