Metadata-Version: 2.4
Name: mt5-bridge
Version: 1.2.0
Summary: MT5 Bridge API - REST API and CLI for MetaTrader5
Project-URL: Homepage, https://github.com/akivajp/mt5-bridge
Project-URL: Repository, https://github.com/akivajp/mt5-bridge
Author-email: Akiva Miura <akiva.miura@gmail.com>
License-File: LICENSE
Requires-Python: >=3.11
Requires-Dist: fastapi>=0.110.0
Requires-Dist: fastmcp>=0.4.1
Requires-Dist: httpx>=0.27.0
Requires-Dist: metatrader5>=5.0.0; sys_platform == 'win32'
Requires-Dist: pandas>=2.0.0
Requires-Dist: pydantic>=2.6.0
Requires-Dist: uvicorn[standard]>=0.29.0
